{
    "title": "France Alzheimer",
    "url": "http://francealzheimer.org",
    "logo": "assets/img/about/france-alzheimer.png",
    "data": {
        "intro": "Association combattant pour faire évoluer l'image de la maladie",
        "text1": "Pour faire évoluer l’image de la maladie, France Alzheimer mène depuis plusieurs années des campagnes de sensibilisation auprès du grand public.",
        "text2": "Nos campagnes ont participé aux efforts de communication entrepris ces dernières années pour améliorer la connaissance du public face au fléau que représente la maladie d’Alzheimer."
    }
}
